hong-0.1.0.dist-info/DESCRIPTION.rst
hong-0.1.0.dist-info/METADATA
hong-0.1.0.dist-info/RECORD
hong-0.1.0.dist-info/WHEEL
hong-0.1.0.dist-info/entry_points.txt
hong-0.1.0.dist-info/metadata.json
hong-0.1.0.dist-info/top_level.txt
stocks/__init__.py
stocks/stocks.py
stocks/data/crypto.csv
stocks/data/my_coins.txt
stocks/data/my_stocks.txt
stocks/data/name_code_list_KOSPI.csv
stocks/data/name_code_list_kosdaq.csv
