Metadata-Version: 2.0
Name: hong
Version: 0.1.0
Summary: UNKNOWN
Home-page: https://github.com/Jyejin/hong
Author: yejinJ
Author-email: dbswjd1977@gmail.com
License: UNKNOWN
Platform: UNKNOWN
Requires-Dist: bs4
Requires-Dist: colorama
Requires-Dist: lxml
Requires-Dist: pandas
Requires-Dist: requests
